sytool/__init__.py
sytool/bloom/__init__.py
sytool/cache/__init__.py
sytool/cache/redis_manager.py
sytool/captcha/__init__.py
sytool/config/__init__.py
sytool/config/config_manager.py
sytool/core/__init__.py
sytool/core/debounce_timer.py
sytool/core/singleton.py
sytool/core/util/__init__.py
sytool/core/util/char_util.py
sytool/core/util/date_util.py
sytool/core/util/escape_util.py
sytool/core/util/file_util.py
sytool/core/util/hex_util.py
sytool/core/util/id_util.py
sytool/core/util/number_util.py
sytool/core/util/object_util.py
sytool/core/util/radix_util.py
sytool/core/util/random_util.py
sytool/core/util/str_util.py
sytool/core/util/zip_util.py
sytool/cypto/__init__.py
sytool/cypto/base64_util.py
sytool/cypto/digest_util.py
sytool/db/__init__.py
sytool/db/sqlbuilder.py
sytool/http/__init__.py
sytool/http/request.py
sytool/io/__init__.py
sytool/io/file_util2.py
sytool/job/__init__.py
sytool/json/__init__.py
sytool/json/json_util.py
sytool/jwt/__init__.py
sytool/log/__init__.py
sytool/log/logger.py
sytool/network/__init__.py
sytool/network/net_util.py
sytool/poi/__init__.py
sytool/random/__init__.py
sytool/socket/__init__.py
sytool/str/__init__.py
sytool/system/__init__.py
sytool/thread/__init__.py
sytool/thread/async_executor.py
sytool/time/__init__.py
sytool-1.0.10.dist-info/METADATA
sytool-1.0.10.dist-info/WHEEL
sytool-1.0.10.dist-info/top_level.txt
sytool-1.0.10.dist-info/RECORD
