Metadata-Version: 2.4
Name: syTool
Version: 1.0.10
Summary: A modular toolkit for database operations, HTTP clients, file processing, caching, and more.
Author-email: Sawyerlsy <sawyerlsy@126.com>
Project-URL: Homepage, https://gitee.com/sawyerlsy/syTool
Keywords: toolkit,database,http,file,cache,utility
Classifier: Development Status :: 4 - Beta
Classifier: Intended Audience :: Developers
Classifier: License :: OSI Approved :: MIT License
Classifier: Programming Language :: Python :: 3
Classifier: Programming Language :: Python :: 3 :: Only
Classifier: Programming Language :: Python :: 3.7
Classifier: Programming Language :: Python :: 3.8
Classifier: Programming Language :: Python :: 3.9
Classifier: Programming Language :: Python :: 3.10
Classifier: Programming Language :: Python :: 3.11
Classifier: Operating System :: OS Independent
Classifier: Topic :: Software Development :: Libraries :: Python Modules
Requires-Python: >=3.11
Requires-Dist: loguru>=0.7.3
Requires-Dist: pytz~=2025.2
Requires-Dist: python-dateutil~=2.9.0.post0
Requires-Dist: orjson>=3.10.18
Provides-Extra: bloom
Provides-Extra: cache-redis
Requires-Dist: redis~=3.5.3; extra == "cache-redis"
Requires-Dist: redis-py-cluster~=2.1.3; extra == "cache-redis"
Provides-Extra: cache-local
Provides-Extra: cache-all
Requires-Dist: syTool[cache-redis]; extra == "cache-all"
Requires-Dist: syTool[cache-local]; extra == "cache-all"
Provides-Extra: captcha
Provides-Extra: config
Requires-Dist: dynaconf~=3.2.11; extra == "config"
Provides-Extra: core
Provides-Extra: cypto
Provides-Extra: db-mysql
Requires-Dist: oracledb>=3.3.0; extra == "db-mysql"
Requires-Dist: pymysql~=1.1.2; extra == "db-mysql"
Provides-Extra: db-oracle
Requires-Dist: sqlalchemy~=2.0.43; extra == "db-oracle"
Requires-Dist: oracledb>=3.3.0; extra == "db-oracle"
Provides-Extra: db-sqlserver
Requires-Dist: sqlalchemy~=2.0.43; extra == "db-sqlserver"
Requires-Dist: pymssql~=2.3.7; extra == "db-sqlserver"
Provides-Extra: db-all
Requires-Dist: syTool[db-mysql]; extra == "db-all"
Requires-Dist: syTool[db-oracle]; extra == "db-all"
Requires-Dist: syTool[db-sqlserver]; extra == "db-all"
Provides-Extra: http
Requires-Dist: requests~=2.32.3; extra == "http"
Requires-Dist: httpx[http2]>=0.28.1; extra == "http"
Requires-Dist: aiofiles>=24.1.0; extra == "http"
Provides-Extra: io
Provides-Extra: job
Requires-Dist: APScheduler~=3.11.0; extra == "job"
Provides-Extra: json
Provides-Extra: jwt
Provides-Extra: log
Provides-Extra: network
Requires-Dist: netifaces~=0.11.0; extra == "network"
Requires-Dist: dnspython~=2.8.0; extra == "network"
Provides-Extra: poi
Provides-Extra: socket
Provides-Extra: str
Provides-Extra: system
Provides-Extra: thread
Provides-Extra: time
Provides-Extra: all
Requires-Dist: syTool[bloom]; extra == "all"
Requires-Dist: syTool[cache-all]; extra == "all"
Requires-Dist: syTool[captcha]; extra == "all"
Requires-Dist: syTool[config]; extra == "all"
Requires-Dist: syTool[core]; extra == "all"
Requires-Dist: syTool[cypto]; extra == "all"
Requires-Dist: syTool[db-all]; extra == "all"
Requires-Dist: syTool[http]; extra == "all"
Requires-Dist: syTool[io]; extra == "all"
Requires-Dist: syTool[job]; extra == "all"
Requires-Dist: syTool[json]; extra == "all"
Requires-Dist: syTool[jwt]; extra == "all"
Requires-Dist: syTool[log]; extra == "all"
Requires-Dist: syTool[network]; extra == "all"
Requires-Dist: syTool[poi]; extra == "all"
Requires-Dist: syTool[socket]; extra == "all"
Requires-Dist: syTool[str]; extra == "all"
Requires-Dist: syTool[system]; extra == "all"
Requires-Dist: syTool[thread]; extra == "all"
Requires-Dist: syTool[time]; extra == "all"
